protclus/__init__.py
protclus/cluster_alg.py
protclus/coach.py
protclus/coach_script.py
protclus/deterministic_ipca.py
protclus/dpclus.py
protclus/dpclus_script.py
protclus/ipca.py
protclus/ipca_script.py
protclus/mcode.py
protclus/mcode_script.py
protclus-0.9.1.dist-info/LICENSE
protclus-0.9.1.dist-info/METADATA
protclus-0.9.1.dist-info/WHEEL
protclus-0.9.1.dist-info/top_level.txt
protclus-0.9.1.dist-info/RECORD
