Metadata-Version: 2.1
Name: protclus
Version: 0.9.1
Summary: protclus: Library for protein complex discovery on PPI networks
Home-page: https://github.com/paulmorio/protclus
Author: Paul Scherer
Author-email: paul.geo2dr@gmail.com
License: MIT
Platform: UNKNOWN
Classifier: Topic :: Scientific/Engineering :: Artificial Intelligence
Classifier: License :: OSI Approved :: MIT License
Classifier: Natural Language :: English
Classifier: Programming Language :: Python :: 3.6
Classifier: Operating System :: OS Independent
Requires-Dist: numpy
Requires-Dist: tqdm
Requires-Dist: networkx
Requires-Dist: py27hash
